cdk_nat_asg_provider/__init__.py
cdk_nat_asg_provider/py.typed
cdk_nat_asg_provider/_jsii/__init__.py
cdk_nat_asg_provider/_jsii/cdk-nat-asg-provider@0.0.5.jsii.tgz
cdk_nat_asg_provider-0.0.5.dist-info/LICENSE
cdk_nat_asg_provider-0.0.5.dist-info/METADATA
cdk_nat_asg_provider-0.0.5.dist-info/WHEEL
cdk_nat_asg_provider-0.0.5.dist-info/top_level.txt
cdk_nat_asg_provider-0.0.5.dist-info/RECORD
