Metadata-Version: 2.1
Name: cdk-nat-asg-provider
Version: 0.0.5
Summary: An AWS CDK library providing NAT instances that are each placed in their own auto scaling group to improve fault tolerance and availability.
Home-page: https://github.com/fonzcastellanos/cdk-nat-asg-provider.git
Author: Alfonso Castellanos<dev@alfonsocastellanos.com>
License: Apache-2.0
Project-URL: Source, https://github.com/fonzcastellanos/cdk-nat-asg-provider.git
Classifier: Intended Audience :: Developers
Classifier: Operating System :: OS Independent
Classifier: Programming Language :: JavaScript
Classifier: Programming Language :: Python :: 3 :: Only
Classifier: Programming Language :: Python :: 3.7
Classifier: Programming Language :: Python :: 3.8
Classifier: Programming Language :: Python :: 3.9
Classifier: Programming Language :: Python :: 3.10
Classifier: Typing :: Typed
Classifier: Development Status :: 4 - Beta
Classifier: License :: OSI Approved
Requires-Python: ~=3.7
License-File: LICENSE
Requires-Dist: aws-cdk-lib (<3.0.0,>=2.26.0)
Requires-Dist: constructs (<11.0.0,>=10.0.5)
Requires-Dist: jsii (<2.0.0,>=1.75.0)
Requires-Dist: publication (>=0.0.3)
Requires-Dist: typeguard (~=2.13.3)
